code_agent/__init__.py
code_agent/cli_entry.py
code_agent/images/image.png
code_agent/src/__init__.py
code_agent/src/agent.py
code_agent/src/app.py
code_agent/src/llm.py
code_agent/src/md_test.py
code_agent/src/prompts.py
code_agent/src/tool_browser.py
code_agent/src/tool_playwright.py
code_agent/src/tools.py
code_agent/tests/TestEnvironment/sample/add.py
code_agent/tests/TestEnvironment/sample/client.py
code_agent/tests/TestEnvironment/sample/ollama_client.py
code_agent/tests/TestEnvironment/sample/server.py
code_agent/tests/run.txt
code_agent/tests/test_cli.py
code_agent/tests/test_edit_tool.py
opencursor-0.0.27.dist-info/METADATA
opencursor-0.0.27.dist-info/WHEEL
opencursor-0.0.27.dist-info/entry_points.txt
opencursor-0.0.27.dist-info/RECORD
